[
    {
        "id": 1,
        "paciente": "kainan",
        "sangue": "o+",
        "quantidade": 10
    },
    {
        "id": 2,
        "paciente": "Vinicius",
        "sangue": "B-",
        "quantidade": 5
    },
    {
        "id": 3,
        "paciente": "Maicon",
        "sangue": "A+",
        "quantidade": 12
    },
    {
        "id": 4,
        "paciente": "Igor JS(VULGO AMARELAO)",
        "sangue": "o-",
        "quantidade": 6
    },
    {
        "id": 5,
        "paciente": "Pedro",
        "sangue": "o+",
        "quantidade": 12
    },
    {
        "id": 6,
        "paciente": "Pedro",
        "sangue": "o+",
        "quantidade": 10
    },
    {
        "id": 7,
        "paciente": "Vini",
        "sangue": "A+",
        "quantidade": 12
    }
]